<?xml version="1.0" encoding="UTF-8" ?>
<r xmlns="http://pear.php.net/dtd/rest.release2" xmlns:xsi="http://www.w3.org/2001/XMLSchema-instance" xmlns:xlink="http://www.w3.org/1999/xlink" xsi:schemaLocation="http://pear.php.net/dtd/rest.release2 http://pear.php.net/dtd/rest.release2.xsd">
    <p xlink:href="/rest/p/smarty3">Smarty3</p>
    <c>pear.ethna.jp</c>
    <v>3.1.8</v>
    <a>3.1.8</a>
    <mp>5.2.0</mp>
    <st>stable</st>
    <l>LGPL</l>
    <m>monte</m>
    <s>PHP Template Engine</s>
    <d>Smarty is a template engine for PHP, facilitating the separation of presentation from application logic.</d>
    <da>2012-03-26 03:08:55</da>
    <n>
PEAR Style Package
 </n>
    <f>150911</f>
    <g>http://pear.ethna.jp/get/Smarty3-3.1.8</g>
    <x xlink:href="package.3.1.8.xml"/>
</r>